{
  "id": "10157302",
  "title": "PROPERAV P-FWB44TB-1 Ultra Slim Tilting 32-55\\\" TV Bracket",
  "brand": "PROPERAV",
  "price": {
    "current": 17.99,
    "was": 24.99,
    "savings": 7
  },
  "rating": {
    "average": 4.4,
    "count": 119
  },
  "images": {
    "gallery": [
      "https://media.electriz.biz/i/electrizprod/10157302?$l-large$&fmt=auto",
      "https://media.electriz.biz/i/electrizprod/10157302_001?$l-large$&fmt=auto",
      "https://media.electriz.biz/i/electrizprod/10157302_002?$l-large$&fmt=auto",
      "https://media.electriz.biz/i/electrizprod/10157302_003?$l-large$&fmt=auto",
      "https://media.electriz.biz/i/electrizprod/10157302_004?$l-large$&fmt=auto",
      "https://media.electriz.biz/i/electrizprod/10157302_005?$l-large$&fmt=auto",
      "https://media.electriz.biz/i/electrizprod/10157302_006?$l-large$&fmt=auto",
      "https://media.electriz.biz/i/electrizprod/10157302_007?$l-large$&fmt=auto",
      "https://media.electriz.biz/i/electrizprod/10157302_008?$l-large$&fmt=auto",
      "https://media.electriz.biz/i/electrizprod/10157302_009?$l-large$&fmt=auto",
      "https://media.electriz.biz/i/electrizprod/10157302_010?$l-large$&fmt=auto"
    ],
    "thumbnails": [
      "https://media.electriz.biz/i/electrizprod/10157302?$t-thumbnail$&fmt=auto",
      "https://media.electriz.biz/i/electrizprod/10157302_001?$t-thumbnail$&fmt=auto",
      "https://media.electriz.biz/i/electrizprod/10157302_002?$t-thumbnail$&fmt=auto",
      "https://media.electriz.biz/i/electrizprod/10157302_003?$t-thumbnail$&fmt=auto",
      "https://media.electriz.biz/i/electrizprod/10157302_004?$t-thumbnail$&fmt=auto",
      "https://media.electriz.biz/i/electrizprod/10157302_005?$t-thumbnail$&fmt=auto",
      "https://media.electriz.biz/i/electrizprod/10157302_006?$t-thumbnail$&fmt=auto",
      "https://media.electriz.biz/i/electrizprod/10157302_007?$t-thumbnail$&fmt=auto",
      "https://media.electriz.biz/i/electrizprod/10157302_008?$t-thumbnail$&fmt=auto",
      "https://media.electriz.biz/i/electrizprod/10157302_009?$t-thumbnail$&fmt=auto",
      "https://media.electriz.biz/i/electrizprod/10157302_010?$t-thumbnail$&fmt=auto"
    ],
    "video": null
  },
  "keySpecs": [
    {
      "icon": "",
      "label": "For 32 - 55” Televisions"
    },
    {
      "icon": "",
      "label": "Max. VESA compliance:"
    },
    {
      "icon": "",
      "label": "Min. VESA compliance:"
    },
    {
      "icon": "",
      "label": "Max. supported weight:"
    }
  ],
  "careAndRepair": [],
  "essentialServices": [],
  "crossSellProducts": [
    {
      "category": "Cables and Accessories",
      "title": "SANDSTROM Black Series S1HDM115 High Speed HDMI Cable with Ethernet - 1 m",
      "price": 19.99,
      "rating": 4.7,
      "reviewCount": 35,
      "image": "/images/products/10132171/main.webp"
    },
    {
      "category": "Cables and Accessories",
      "title": "LOGIK L3WAYSP18 3-Socket Plug Adapter",
      "price": 9.99,
      "rating": 4.6,
      "reviewCount": 49,
      "image": "/images/products/10173550/main.webp"
    }
  ],
  "offers": [],
  "badges": [],
  "specifications": {},
  "description": {
    "main": "Enhance your setup with the PROPERAV P-FWB44TB-1 Ultra Slim Tilting 32-55\\\" TV Bracket. Featuring for 32 - 55” televisions, max. vesa compliance:, min. vesa compliance:, this accessory is designed to complement your TV viewing experience.",
    "goodToKnow": [
      "Free standard delivery",
      "2 year guarantee included"
    ]
  },
  "deliveryInfo": {
    "freeDelivery": true,
    "standardDeliveryPrice": 0,
    "nextDayDeliveryPrice": 5.99,
    "standardDeliveryDays": "3-5"
  },
  "category": "TV Accessories",
  "lastUpdated": "2026-03-06T15:49:44.753Z"
}