{
  "id": "10266704",
  "title": "HOUSE OF MARLEY Positive Vibration Frequency Wireless Bluetooth Headphones - Copper",
  "brand": "HOUSE",
  "price": {
    "current": 99.99,
    "was": null,
    "savings": null
  },
  "rating": {
    "average": 0,
    "count": 0
  },
  "images": {
    "gallery": [
      "https://media.electriz.biz/i/electrizprod/10266704?$l-large$&fmt=auto",
      "https://media.electriz.biz/i/electrizprod/10266704_001?$l-large$&fmt=auto",
      "https://media.electriz.biz/i/electrizprod/10266704_002?$l-large$&fmt=auto",
      "https://media.electriz.biz/i/electrizprod/10266704_003?$l-large$&fmt=auto",
      "https://media.electriz.biz/i/electrizprod/10266704_004?$l-large$&fmt=auto",
      "https://media.electriz.biz/i/electrizprod/10266704_005?$l-large$&fmt=auto",
      "https://media.electriz.biz/i/electrizprod/10266704_006?$l-large$&fmt=auto",
      "https://media.electriz.biz/i/electrizprod/10266704_007?$l-large$&fmt=auto",
      "https://media.electriz.biz/i/electrizprod/10266704_008?$l-large$&fmt=auto",
      "https://media.electriz.biz/i/electrizprod/10266704_009?$l-large$&fmt=auto",
      "https://media.electriz.biz/i/electrizprod/10266704_010?$l-large$&fmt=auto"
    ],
    "thumbnails": [
      "https://media.electriz.biz/i/electrizprod/10266704?$t-thumbnail$&fmt=auto",
      "https://media.electriz.biz/i/electrizprod/10266704_001?$t-thumbnail$&fmt=auto",
      "https://media.electriz.biz/i/electrizprod/10266704_002?$t-thumbnail$&fmt=auto",
      "https://media.electriz.biz/i/electrizprod/10266704_003?$t-thumbnail$&fmt=auto",
      "https://media.electriz.biz/i/electrizprod/10266704_004?$t-thumbnail$&fmt=auto",
      "https://media.electriz.biz/i/electrizprod/10266704_005?$t-thumbnail$&fmt=auto",
      "https://media.electriz.biz/i/electrizprod/10266704_006?$t-thumbnail$&fmt=auto",
      "https://media.electriz.biz/i/electrizprod/10266704_007?$t-thumbnail$&fmt=auto",
      "https://media.electriz.biz/i/electrizprod/10266704_008?$t-thumbnail$&fmt=auto",
      "https://media.electriz.biz/i/electrizprod/10266704_009?$t-thumbnail$&fmt=auto",
      "https://media.electriz.biz/i/electrizprod/10266704_010?$t-thumbnail$&fmt=auto"
    ],
    "video": null
  },
  "keySpecs": [
    {
      "icon": "",
      "label": "Over-ear headphones"
    },
    {
      "icon": "",
      "label": "Battery life:"
    },
    {
      "icon": "",
      "label": "Microphone / volume / playback & functions control"
    },
    {
      "icon": "",
      "label": "2 year guarantee"
    }
  ],
  "careAndRepair": [
    {
      "plan": "Recycle my old tech",
      "price": 20,
      "period": "One-time fee"
    }
  ],
  "essentialServices": [],
  "crossSellProducts": [],
  "offers": [],
  "badges": [],
  "specifications": {},
  "description": {
    "main": "Enjoy premium audio with the HOUSE OF MARLEY Positive Vibration Frequency Wireless Bluetooth Headphones - Copper. Featuring over-ear headphones, battery life:, microphone / volume / playback & functions control, these headphones deliver exceptional sound quality for music, calls, and entertainment.",
    "goodToKnow": [
      "Free standard delivery",
      "2 year guarantee included"
    ]
  },
  "deliveryInfo": {
    "freeDelivery": true,
    "standardDeliveryPrice": 0,
    "nextDayDeliveryPrice": 5.99,
    "standardDeliveryDays": "3-5"
  },
  "category": "Headphones",
  "lastUpdated": "2026-03-06T15:49:44.753Z"
}