{
  "id": "10263880",
  "title": "SAMSUNG HW-S60D/XU 5.0 All-in-One Sound Bar with Dolby Atmos, DTS Virtual:X & Amazon Alexa - Black",
  "brand": "Samsung",
  "price": {
    "current": 389,
    "was": 399,
    "savings": 10
  },
  "rating": {
    "average": 4.6,
    "count": 198
  },
  "images": {
    "gallery": [
      "https://media.electriz.biz/i/electrizprod/10263880_004?$l-large$&fmt=auto",
      "https://media.electriz.biz/i/electrizprod/10263880?$l-large$&fmt=auto",
      "https://media.electriz.biz/i/electrizprod/10263880_001?$l-large$&fmt=auto",
      "https://media.electriz.biz/i/electrizprod/10263880_002?$l-large$&fmt=auto",
      "https://media.electriz.biz/i/electrizprod/10263880_003?$l-large$&fmt=auto"
    ],
    "thumbnails": [
      "https://media.electriz.biz/i/electrizprod/10263880?$t-thumbnail$&fmt=auto",
      "https://media.electriz.biz/i/electrizprod/10263880_001?$t-thumbnail$&fmt=auto",
      "https://media.electriz.biz/i/electrizprod/10263880_002?$t-thumbnail$&fmt=auto",
      "https://media.electriz.biz/i/electrizprod/10263880_003?$t-thumbnail$&fmt=auto",
      "https://media.electriz.biz/i/electrizprod/10263880_004?$t-thumbnail$&fmt=auto"
    ],
    "video": null
  },
  "keySpecs": [
    {
      "icon": "",
      "label": "Number of speakers: 7"
    },
    {
      "icon": "",
      "label": "Dolby Atmos & DTS Virtual:X"
    },
    {
      "icon": "",
      "label": "Built-in subwoofer"
    },
    {
      "icon": "",
      "label": "Audio power: 200 W"
    },
    {
      "icon": "",
      "label": "Adaptive / optimized audio"
    },
    {
      "icon": "",
      "label": "HDMI"
    }
  ],
  "careAndRepair": [
    {
      "plan": "Care & Repair",
      "price": 4.67,
      "period": "per month",
      "mostPopular": true
    },
    {
      "plan": "Installation",
      "price": 45,
      "period": "One-time fee"
    },
    {
      "plan": "Recycle my old tech",
      "price": 20,
      "period": "One-time fee"
    }
  ],
  "essentialServices": [],
  "crossSellProducts": [],
  "offers": [],
  "badges": [],
  "specifications": {},
  "description": {
    "main": "Take movie night up a notch with this Samsung S60D sound bar.",
    "features": [
      "Number of speakers: 7",
      "Dolby Atmos & DTS Virtual:X",
      "Built-in subwoofer",
      "Audio power: 200 W"
    ]
  },
  "deliveryInfo": {
    "freeDelivery": true,
    "standardDeliveryPrice": 0,
    "nextDayDeliveryPrice": 0,
    "standardDeliveryDays": "3-5"
  },
  "category": "Soundbars",
  "lastUpdated": "2026-03-06T15:49:44.753Z",
  "galleryImages": [
    "https://cdn.media.amplience.net/i/electrizprod/10263880?$l-large$&fmt=auto",
    "https://cdn.media.amplience.net/i/electrizprod/10263880_001?$l-large$&fmt=auto"
  ]
}
