{
  "id": "10279083",
  "title": "MIXX StreamQ Wireless Bluetooth Headphones - Black",
  "brand": "MIXX",
  "price": {
    "current": 60.99,
    "was": null,
    "savings": null
  },
  "rating": {
    "average": 0,
    "count": 0
  },
  "images": {
    "gallery": [
      "https://media.electriz.biz/i/electrizprod/10279083?$l-large$&fmt=auto",
      "https://media.electriz.biz/i/electrizprod/10279083_001?$l-large$&fmt=auto",
      "https://media.electriz.biz/i/electrizprod/10279083_002?$l-large$&fmt=auto",
      "https://media.electriz.biz/i/electrizprod/10279083_003?$l-large$&fmt=auto",
      "https://media.electriz.biz/i/electrizprod/10279083_004?$l-large$&fmt=auto",
      "https://media.electriz.biz/i/electrizprod/10279083_005?$l-large$&fmt=auto",
      "https://media.electriz.biz/i/electrizprod/10279083_006?$l-large$&fmt=auto",
      "https://media.electriz.biz/i/electrizprod/10279083_007?$l-large$&fmt=auto",
      "https://media.electriz.biz/i/electrizprod/10279083_008?$l-large$&fmt=auto",
      "https://media.electriz.biz/i/electrizprod/10279083_009?$l-large$&fmt=auto",
      "https://media.electriz.biz/i/electrizprod/10279083_010?$l-large$&fmt=auto"
    ],
    "thumbnails": [
      "https://media.electriz.biz/i/electrizprod/10279083?$t-thumbnail$&fmt=auto",
      "https://media.electriz.biz/i/electrizprod/10279083_001?$t-thumbnail$&fmt=auto",
      "https://media.electriz.biz/i/electrizprod/10279083_002?$t-thumbnail$&fmt=auto",
      "https://media.electriz.biz/i/electrizprod/10279083_003?$t-thumbnail$&fmt=auto",
      "https://media.electriz.biz/i/electrizprod/10279083_004?$t-thumbnail$&fmt=auto",
      "https://media.electriz.biz/i/electrizprod/10279083_005?$t-thumbnail$&fmt=auto",
      "https://media.electriz.biz/i/electrizprod/10279083_006?$t-thumbnail$&fmt=auto",
      "https://media.electriz.biz/i/electrizprod/10279083_007?$t-thumbnail$&fmt=auto",
      "https://media.electriz.biz/i/electrizprod/10279083_008?$t-thumbnail$&fmt=auto",
      "https://media.electriz.biz/i/electrizprod/10279083_009?$t-thumbnail$&fmt=auto",
      "https://media.electriz.biz/i/electrizprod/10279083_010?$t-thumbnail$&fmt=auto"
    ],
    "video": null
  },
  "keySpecs": [
    {
      "icon": "",
      "label": "Over-ear headphones"
    },
    {
      "icon": "",
      "label": "Battery life:"
    },
    {
      "icon": "",
      "label": "Foldable"
    },
    {
      "icon": "",
      "label": "Microphone / volume / playback & functions control"
    },
    {
      "icon": "",
      "label": "2 year guarantee"
    }
  ],
  "careAndRepair": [
    {
      "plan": "Recycle my old tech",
      "price": 20,
      "period": "One-time fee"
    }
  ],
  "essentialServices": [],
  "crossSellProducts": [
    {
      "category": "Cables",
      "title": "BELKIN Braided USB-C to USB-A Cable - 1 m",
      "price": 10.39,
      "wasPrice": 12.99,
      "savings": 2.6,
      "rating": 4.7,
      "reviewCount": 26,
      "image": "/images/products/10206906/main.webp"
    },
    {
      "category": "Headphones",
      "title": "SONY WH-CH520B Wireless Bluetooth Headphones - Black",
      "price": 34.99,
      "rating": 4.7,
      "reviewCount": 305,
      "image": "/images/products/10247634/main.webp"
    },
    {
      "category": "Earphones",
      "title": "SONY IER-EX15C USB-C Earphones - Black",
      "price": 19.99,
      "rating": 4.4,
      "reviewCount": 8,
      "image": "/images/products/10291756/main.webp"
    }
  ],
  "offers": [],
  "badges": [],
  "specifications": {},
  "description": {
    "main": "Enjoy premium audio with the MIXX StreamQ Wireless Bluetooth Headphones - Black. Featuring over-ear headphones, battery life:, foldable, these headphones deliver exceptional sound quality for music, calls, and entertainment.",
    "goodToKnow": [
      "Free standard delivery",
      "2 year guarantee included"
    ]
  },
  "deliveryInfo": {
    "freeDelivery": true,
    "standardDeliveryPrice": 0,
    "nextDayDeliveryPrice": 5.99,
    "standardDeliveryDays": "3-5"
  },
  "category": "Headphones",
  "lastUpdated": "2026-03-06T15:49:44.753Z"
}