{"id":"10283886","title":"HISENSE A6Q 55\" LED 4K HDR Smart TV with Freely","brand":"HISENSE","price":{"current":349,"was":449,"savings":100},"rating":{"average":4.8,"count":3899},"images":{"gallery":["https://media.currys.biz/i/currysprod/10283886?$l-large$&fmt=auto","https://media.currys.biz/i/currysprod/10283886_001?$l-large$&fmt=auto","https://media.currys.biz/i/currysprod/10283886_002?$l-large$&fmt=auto","https://media.currys.biz/i/currysprod/10283886_003?$l-large$&fmt=auto","https://media.currys.biz/i/currysprod/10283886_004?$l-large$&fmt=auto","https://media.currys.biz/i/currysprod/10283886_005?$l-large$&fmt=auto","https://media.currys.biz/i/currysprod/10283886_006?$l-large$&fmt=auto","https://media.currys.biz/i/currysprod/10283886_007?$l-large$&fmt=auto","https://media.currys.biz/i/currysprod/10283886_008?$l-large$&fmt=auto","https://media.currys.biz/i/currysprod/10283886_009?$l-large$&fmt=auto","https://media.currys.biz/i/currysprod/10283886_010?$l-large$&fmt=auto"],"thumbnails":["https://media.currys.biz/i/currysprod/10283886?$t-thumbnail$&fmt=auto","https://media.currys.biz/i/currysprod/10283886_001?$t-thumbnail$&fmt=auto","https://media.currys.biz/i/currysprod/10283886_002?$t-thumbnail$&fmt=auto","https://media.currys.biz/i/currysprod/10283886_003?$t-thumbnail$&fmt=auto","https://media.currys.biz/i/currysprod/10283886_004?$t-thumbnail$&fmt=auto","https://media.currys.biz/i/currysprod/10283886_005?$t-thumbnail$&fmt=auto","https://media.currys.biz/i/currysprod/10283886_006?$t-thumbnail$&fmt=auto","https://media.currys.biz/i/currysprod/10283886_007?$t-thumbnail$&fmt=auto","https://media.currys.biz/i/currysprod/10283886_008?$t-thumbnail$&fmt=auto","https://media.currys.biz/i/currysprod/10283886_009?$t-thumbnail$&fmt=auto","https://media.currys.biz/i/currysprod/10283886_010?$t-thumbnail$&fmt=auto"],"video":null},"keySpecs":[{"icon":"","label":"4K Direct Lit Full Array: gives vivid colours & deep blacks"},{"icon":"","label":"Hi-View Engine: continuously optimises and enhances content"},{"icon":"","label":"Refresh rate: 60 Hz"},{"icon":"","label":"HDMI 2.1 x 3"},{"icon":"","label":"2 year guarantee"},{"icon":"","label":"Freely: Stream live & on demand TV for free"}],"flexpay":{"monthlyAmount":14.8,"months":36,"totalPayable":532.67,"apr":"29.9%"},"careAndRepair":[{"plan":"Care & Repair","price":4.19,"period":"per month","mostPopular":true},{"plan":"Installation","price":45,"period":"One-time fee"},{"plan":"Recycle my old tech","price":20,"period":"One-time fee"}],"essentialServices":[],"crossSellProducts":[],"offers":[],"badges":[],"specifications":{},"description":{"main":"Experience stunning visuals with the HISENSE A6Q 55\" LED 4K HDR Smart TV with Freely. Featuring 4k direct lit full array: gives vivid colours & deep blacks, hi-view engine: continuously optimises and enhances content, refresh rate: 60 hz, this HISENSE TV delivers an immersive viewing experience for movies, gaming, and everyday entertainment.","goodToKnow":["Free standard delivery","2 year guarantee included"]},"deliveryInfo":{"freeDelivery":true,"standardDeliveryPrice":0,"nextDayDeliveryPrice":9.99,"standardDeliveryDays":"3-5"},"category":"TVs","energyRating":"E"}