{
  "id": "10282145",
  "title": "LG QNED82 65\\\" QNED AI 4K HDR Smart TV 2025 - 65QNED82A6B",
  "brand": "LG",
  "price": {
    "current": 699,
    "was": 999,
    "savings": 300
  },
  "rating": {
    "average": 4.4,
    "count": 41
  },
  "images": {
    "gallery": [
      "https://media.electriz.biz/i/electrizprod/10282145?$l-large$&fmt=auto",
      "https://media.electriz.biz/i/electrizprod/10282145_001?$l-large$&fmt=auto",
      "https://media.electriz.biz/i/electrizprod/10282145_002?$l-large$&fmt=auto",
      "https://media.electriz.biz/i/electrizprod/10282145_003?$l-large$&fmt=auto",
      "https://media.electriz.biz/i/electrizprod/10282145_004?$l-large$&fmt=auto",
      "https://media.electriz.biz/i/electrizprod/10282145_005?$l-large$&fmt=auto",
      "https://media.electriz.biz/i/electrizprod/10282145_006?$l-large$&fmt=auto",
      "https://media.electriz.biz/i/electrizprod/10282145_007?$l-large$&fmt=auto",
      "https://media.electriz.biz/i/electrizprod/10282145_008?$l-large$&fmt=auto",
      "https://media.electriz.biz/i/electrizprod/10282145_009?$l-large$&fmt=auto",
      "https://media.electriz.biz/i/electrizprod/10282145_010?$l-large$&fmt=auto"
    ],
    "thumbnails": [
      "https://media.electriz.biz/i/electrizprod/10282145?$t-thumbnail$&fmt=auto",
      "https://media.electriz.biz/i/electrizprod/10282145_001?$t-thumbnail$&fmt=auto",
      "https://media.electriz.biz/i/electrizprod/10282145_002?$t-thumbnail$&fmt=auto",
      "https://media.electriz.biz/i/electrizprod/10282145_003?$t-thumbnail$&fmt=auto",
      "https://media.electriz.biz/i/electrizprod/10282145_004?$t-thumbnail$&fmt=auto",
      "https://media.electriz.biz/i/electrizprod/10282145_005?$t-thumbnail$&fmt=auto",
      "https://media.electriz.biz/i/electrizprod/10282145_006?$t-thumbnail$&fmt=auto",
      "https://media.electriz.biz/i/electrizprod/10282145_007?$t-thumbnail$&fmt=auto",
      "https://media.electriz.biz/i/electrizprod/10282145_008?$t-thumbnail$&fmt=auto",
      "https://media.electriz.biz/i/electrizprod/10282145_009?$t-thumbnail$&fmt=auto",
      "https://media.electriz.biz/i/electrizprod/10282145_010?$t-thumbnail$&fmt=auto"
    ],
    "video": null
  },
  "keySpecs": [
    {
      "icon": "",
      "label": "Dynamic QNED colour technology for rich & accurate colours"
    },
    {
      "icon": "",
      "label": "Smart a7 AI Processor for enhanced picture & sound"
    },
    {
      "icon": "",
      "label": "Refresh rate:"
    },
    {
      "icon": "",
      "label": "HDMI 2.0 x 3"
    },
    {
      "icon": "",
      "label": "LG’s webOS gives you easy access to all your must-have apps"
    },
    {
      "icon": "",
      "label": "HDR:"
    },
    {
      "icon": "",
      "label": "2 year guarantee"
    }
  ],
  "careAndRepair": [
    {
      "plan": "Care & Repair",
      "price": 8.39,
      "period": "per month",
      "mostPopular": true
    },
    {
      "plan": "Installation",
      "price": 65,
      "period": "One-time fee"
    },
    {
      "plan": "Recycle my old tech",
      "price": 20,
      "period": "One-time fee"
    }
  ],
  "essentialServices": [],
  "crossSellProducts": [
    {
      "category": "Home Audio",
      "title": "LG US70TR 5.1.1 Wireless Sound Bar with Dolby Atmos",
      "price": 699,
      "rating": 4.8,
      "reviewCount": 49,
      "image": "/images/products/10262662/main.webp",
      "badge": "Currys Recommends"
    },
    {
      "category": "Cables",
      "title": "LOGIK LCMK123 Cable Management Kit",
      "price": 9.99,
      "rating": 5,
      "reviewCount": 1,
      "image": "/images/products/10245806/main.webp",
      "badge": "Currys Recommends"
    },
    {
      "category": "Cleaning",
      "title": "SANDSTROM S150AVC20 Screen Cleaner",
      "price": 7.99,
      "rating": 4.5,
      "reviewCount": 31,
      "image": "/images/products/10211694/main.webp",
      "badge": "Currys Recommends"
    }
  ],
  "offers": [
    "Claim £100 cashback on this TV.+4 more offers"
  ],
  "badges": [],
  "specifications": {},
  "description": {
    "main": "Experience stunning visuals with the LG QNED82 65\\\" QNED AI 4K HDR Smart TV 2025 - 65QNED82A6B. Featuring dynamic qned colour technology for rich & accurate colours, smart a7 ai processor for enhanced picture & sound, refresh rate:, this LG TV delivers an immersive viewing experience for movies, gaming, and everyday entertainment.",
    "goodToKnow": [
      "Free standard delivery",
      "2 year guarantee included"
    ]
  },
  "deliveryInfo": {
    "freeDelivery": true,
    "standardDeliveryPrice": 0,
    "nextDayDeliveryPrice": 9.99,
    "standardDeliveryDays": "3-5"
  },
  "category": "TVs",
  "lastUpdated": "2026-03-06T15:49:44.753Z",
  "bundleDeals": [
    {
      "title": "Buy together and save",
      "items": [
        "LG US70TR 5.1.1 Wireless Sound Bar with Dolby Atmos",
        "LOGIK LCMK123 Cable Management Kit",
        "SANDSTROM S150AVC20 Screen Cleaner"
      ],
      "totalPrice": 699,
      "savings": 300
    }
  ]
}