{
  "brand": "Hisense",
  "price": {
    "current": 749,
    "was": null,
    "savings": null
  },
  "rating": {
    "average": 4.8,
    "count": 929
  },
  "description": {
    "main": "Experience over a billion shades of colour with Quantum Dot technology.",
    "features": [
      "Quantum Dot Colour",
      "Hi-View AI Engine",
      "144 Hz Game Mode PRO",
      "Dolby Vision",
      "Dolby Atmos"
    ],
    "goodToKnow": [
      "5 year guarantee.",
      "Stream live & on-demand TV for free with Freely.",
      "Supports HDMI 2.1"
    ]
  },
  "images": {
    "gallery": [
      "https://cdn.media.amplience.net/i/electrizprod/10282797?$l-large$&fmt=auto",
      "https://cdn.media.amplience.net/i/electrizprod/10282797_001?$l-large$&fmt=auto",
      "https://cdn.media.amplience.net/i/electrizprod/10282797_002?$l-large$&fmt=auto",
      "https://cdn.media.amplience.net/i/electrizprod/10282797_003?$l-large$&fmt=auto",
      "https://cdn.media.amplience.net/i/electrizprod/10282797_004?$l-large$&fmt=auto",
      "https://cdn.media.amplience.net/i/electrizprod/10282797_005?$l-large$&fmt=auto",
      "https://cdn.media.amplience.net/i/electrizprod/10282797_006?$l-large$&fmt=auto",
      "https://cdn.media.amplience.net/i/electrizprod/10282797_007?$l-large$&fmt=auto",
      "https://cdn.media.amplience.net/i/electrizprod/10282797_008?$l-large$&fmt=auto",
      "https://cdn.media.amplience.net/i/electrizprod/10282797_009?$l-large$&fmt=auto",
      "https://cdn.media.amplience.net/i/electrizprod/10282797_010?$l-large$&fmt=auto",
      "https://cdn.media.amplience.net/i/electrizprod/10282797_011?$l-large$&fmt=auto",
      "https://cdn.media.amplience.net/i/electrizprod/10282797_012?$l-large$&fmt=auto",
      "https://cdn.media.amplience.net/i/electrizprod/10282797_013?$l-large$&fmt=auto",
      "https://cdn.media.amplience.net/i/electrizprod/10282797_014?$l-large$&fmt=auto",
      "https://cdn.media.amplience.net/i/electrizprod/10282797_015?$l-large$&fmt=auto"
    ],
    "thumbnails": [
      "https://cdn.media.amplience.net/i/electrizprod/10282797?$t-thumbnail$&fmt=auto",
      "https://cdn.media.amplience.net/i/electrizprod/10282797_001?$t-thumbnail$&fmt=auto",
      "https://cdn.media.amplience.net/i/electrizprod/10282797_002?$t-thumbnail$&fmt=auto",
      "https://cdn.media.amplience.net/i/electrizprod/10282797_003?$t-thumbnail$&fmt=auto",
      "https://cdn.media.amplience.net/i/electrizprod/10282797_004?$t-thumbnail$&fmt=auto",
      "https://cdn.media.amplience.net/i/electrizprod/10282797_005?$t-thumbnail$&fmt=auto",
      "https://cdn.media.amplience.net/i/electrizprod/10282797_006?$t-thumbnail$&fmt=auto",
      "https://cdn.media.amplience.net/i/electrizprod/10282797_007?$t-thumbnail$&fmt=auto",
      "https://cdn.media.amplience.net/i/electrizprod/10282797_008?$t-thumbnail$&fmt=auto",
      "https://cdn.media.amplience.net/i/electrizprod/10282797_009?$t-thumbnail$&fmt=auto",
      "https://cdn.media.amplience.net/i/electrizprod/10282797_010?$t-thumbnail$&fmt=auto",
      "https://cdn.media.amplience.net/i/electrizprod/10282797_011?$t-thumbnail$&fmt=auto",
      "https://cdn.media.amplience.net/i/electrizprod/10282797_012?$t-thumbnail$&fmt=auto",
      "https://cdn.media.amplience.net/i/electrizprod/10282797_013?$t-thumbnail$&fmt=auto",
      "https://cdn.media.amplience.net/i/electrizprod/10282797_014?$t-thumbnail$&fmt=auto",
      "https://cdn.media.amplience.net/i/electrizprod/10282797_015?$t-thumbnail$&fmt=auto"
    ]
  },
  "keySpecs": [
    "Screen size: 65 inch",
    "Display Type: QLED",
    "Resolution: 4K Ultra HD",
    "Refresh Rate: 120 Hz (up to 144 Hz)",
    "Audio Power: 20 W",
    "HDMI: 4"
  ],
  "specifications": {},
  "deliveryInfo": {
    "freeDelivery": false,
    "standardDeliveryPrice": 20,
    "nextDayDeliveryPrice": 30
  },
  "sizeVariants": [
    {
      "size": "65\"",
      "price": 749
    }
  ],
  "crossSellProducts": [],
  "careAndRepair": [
    {
      "name": "Breakdown support",
      "price": 3.5,
      "description": "Monthly plan for fast repairs and replacements."
    }
  ],
  "offers": [
    "Get 20% off marked price on this product. Just enter code 20OFFVIS at checkout."
  ],
  "badges": [
    "Free standard delivery on orders over £40",
    "FREE recycling on selected TVs"
  ],
  "energyRating": "E",
  "category": "TVs",
  "id": "10282797",
  "title": "HISENSE E7Q PRO 65\" QLED 4K HDR Smart TV with Freely - 65E7QTUK PRO",
  "lastUpdated": "2026-03-06T15:49:44.753Z"
}
